flatbuffers/__init__.py
flatbuffers/_version.py
flatbuffers/builder.py
flatbuffers/compat.py
flatbuffers/encode.py
flatbuffers/flexbuffers.py
flatbuffers/number_types.py
flatbuffers/packer.py
flatbuffers/table.py
flatbuffers/util.py
flatbuffers-23.1.20.dist-info/METADATA
flatbuffers-23.1.20.dist-info/WHEEL
flatbuffers-23.1.20.dist-info/top_level.txt
flatbuffers-23.1.20.dist-info/RECORD
